Workbook

Sheet Dashboard
B2: Marketing Campaign Performance Dashboard
B4: Channel: | C4: All | E4: Region: | F4: All | H4: Date From: | I4: 45636 | K4: Date To: | L4: 45818
B5: TOTAL_SPEND | D5: TOTAL_REVENUE | F5: TOTAL_CONVERSIONS | H5: OVERALL_ROAS | J5: AVG_CTR | L5: TOTAL_PROFIT
B6: =SUMIFS(KPI_Data!F2:F501,KPI_Data!C2:C501,IF($C$4="All","*",$C$4),KPI_Data!D2:D501,IF($F$4="All","*",$F$4),KPI_Data!B2:B501,">="&$I$4,KPI_Data!B2:B501,"<="&$L$4) -> 3132508.2 | D6: =SUMIFS(KPI_Data!J2:J501,KPI_Data!C2:C501,IF($C$4="All","*",$C$4),KPI_Data!D2:D501,IF($F$4="All","*",$F$4),KPI_Data!B2:B501,">="&$I$4,KPI_Data!B2:B501,"<="&$L$4) -> 6552948.1 | F6: =SUMIFS(KPI_Data!I2:I501,KPI_Data!C2:C501,IF($C$4="All","*",$C$4),KPI_Data!D2:D501,IF($F$4="All","*",$F$4),KPI_Data!B2:B501,">="&$I$4,KPI_Data!B2:B501,"<="&$L$4) -> 184526 | H6: =IFERROR(D6/B6,0) -> 2.0919173 | J6: =IFERROR(AVERAGEIFS(KPI_Data!K2:K501,KPI_Data!C2:C501,IF($C$4="All","*",$C$4),KPI_Data!D2:D501,IF($F$4="All","*",$F$4),KPI_Data!B2:B501,">="&$I$4,KPI_Data!B2:B501,"<="&$L$4),0) -> 0.029534968 | L6: =SUMIFS(KPI_Data!O2:O501,KPI_Data!C2:C501,IF($C$4="All","*",$C$4),KPI_Data!D2:D501,IF($F$4="All","*",$F$4),KPI_Data!B2:B501,">="&$I$4,KPI_Data!B2:B501,"<="&$L$4) -> 3420439.9

Sheet Pivot_Analysis
C3: Region
A4: Channel | B4: Data | C4: East | D4: North | E4: South | F4: West | G4: Total Result
A5: Facebook
B6: Sum - Spend ($) | C6: 116793.22 | D6: 138263.68 | E6: 151935.91 | F6: 165207.3 | G6: 572200.11
B7: Sum - Revenue ($) | C7: 191813.53 | D7: 378763.59 | E7: 369076.61 | F7: 346251.2 | G7: 1285904.9
B8: Sum - Conversions | C8: 5272 | D8: 9759 | E8: 10175 | F8: 10256 | G8: 35462
A9: Google Ads
B10: Sum - Spend ($) | C10: 149016.4 | D10: 156211.25 | E10: 155849.41 | F10: 176531.44 | G10: 637608.5
B11: Sum - Revenue ($) | C11: 350593.43 | D11: 287928.78 | E11: 318365.2 | F11: 414987.27 | G11: 1371874.7
B12: Sum - Conversions | C12: 9645 | D12: 8332 | E12: 9048 | F12: 11454 | G12: 38479
A13: Instagram
B14: Sum - Spend ($) | C14: 146568.35 | D14: 149657.53 | E14: 187265.72 | F14: 133307.13 | G14: 616798.73
B15: Sum - Revenue ($) | C15: 346381.19 | D15: 331816.25 | E15: 475040.66 | F15: 260499.9 | G15: 1413738
B16: Sum - Conversions | C16: 9666 | D16: 8934 | E16: 13949 | F16: 7054 | G16: 39603
A17: LinkedIn
B18: Sum - Spend ($) | C18: 161487.07 | D18: 210704.04 | E18: 130130.16 | F18: 149798.02 | G18: 652119.29
B19: Sum - Revenue ($) | C19: 334511.72 | D19: 385254.24 | E19: 214236.66 | F19: 353788.6 | G19: 1287791.2
B20: Sum - Conversions | C20: 10136 | D20: 10586 | E20: 6498 | F20: 9350 | G20: 36570
A21: Twitter
B22: Sum - Spend ($) | C22: 137837.84 | D22: 183838.94 | E22: 146228.88 | F22: 185875.9 | G22: 653781.56
B23: Sum - Revenue ($) | C23: 207793.44 | D23: 322917 | E23: 285891.59 | F23: 377037.22 | G23: 1193639.2
B24: Sum - Conversions | C24: 6741 | D24: 9160 | E24: 7918 | F24: 10593 | G24: 34412
A25: Total Sum - Spend ($) | C25: 711702.88 | D25: 838675.44 | E25: 771410.08 | F25: 810719.79 | G25: 3132508.2
A26: Total Sum - Revenue ($) | C26: 1431093.3 | D26: 1706679.9 | E26: 1662610.7 | F26: 1752564.2 | G26: 6552948.1
A27: Total Sum - Conversions | C27: 41460 | D27: 46771 | E27: 47588 | F27: 48707 | G27: 184526

Sheet Summary
A1: Marketing Campaign Performance
A3: Channel-wise Performance
A4: Channel | B4: Spend ($) | C4: Revenue ($) | D4: Conversions | E4: ROAS | F4: Profit ($)
A5: Facebook | B5: =SUMIFS(KPI_Data!$F$2:$F$501,KPI_Data!$C$2:$C$501,A5,KPI_Data!$C$2:$C$501,IF(Dashboard!$C$4="All","*",Dashboard!$C$4),KPI_Data!$D$2:$D$501,IF(Dashboard!$F$4="All","*",Dashboard!$F$4),KPI_Data!$B$2:$B$501,">="&Dashboard!$I$4,KPI_Data!$B$2:$B$501,"<="&Dashboard!$L$4) -> 572200.11 | C5: =SUMIFS(KPI_Data!$J$2:$J$501,KPI_Data!$C$2:$C$501,A5,KPI_Data!$C$2:$C$501,IF(Dashboard!$C$4="All","*",Dashboard!$C$4),KPI_Data!$D$2:$D$501,IF(Dashboard!$F$4="All","*",Dashboard!$F$4),KPI_Data!$B$2:$B$501,">="&Dashboard!$I$4,KPI_Data!$B$2:$B$501,"<="&Dashboard!$L$4) -> 1285904.9 | D5: =SUMIFS(KPI_Data!$I$2:$I$501,KPI_Data!$C$2:$C$501,A5,KPI_Data!$C$2:$C$501,IF(Dashboard!$C$4="All","*",Dashboard!$C$4),KPI_Data!$D$2:$D$501,IF(Dashboard!$F$4="All","*",Dashboard!$F$4),KPI_Data!$B$2:$B$501,">="&Dashboard!$I$4,KPI_Data!$B$2:$B$501,"<="&Dashboard!$L$4) -> 35462 | E5: =IFERROR(C5/B5,0) -> 2.2472993 | F5: =C5-B5 -> 713704.82
A6: Google Ads | B6: =SUMIFS(KPI_Data!$F$2:$F$501,KPI_Data!$C$2:$C$501,A6,KPI_Data!$C$2:$C$501,IF(Dashboard!$C$4="All","*",Dashboard!$C$4),KPI_Data!$D$2:$D$501,IF(Dashboard!$F$4="All","*",Dashboard!$F$4),KPI_Data!$B$2:$B$501,">="&Dashboard!$I$4,KPI_Data!$B$2:$B$501,"<="&Dashboard!$L$4) -> 637608.5 | C6: =SUMIFS(KPI_Data!$J$2:$J$501,KPI_Data!$C$2:$C$501,A6,KPI_Data!$C$2:$C$501,IF(Dashboard!$C$4="All","*",Dashboard!$C$4),KPI_Data!$D$2:$D$501,IF(Dashboard!$F$4="All","*",Dashboard!$F$4),KPI_Data!$B$2:$B$501,">="&Dashboard!$I$4,KPI_Data!$B$2:$B$501,"<="&Dashboard!$L$4) -> 1371874.7 | D6: =SUMIFS(KPI_Data!$I$2:$I$501,KPI_Data!$C$2:$C$501,A6,KPI_Data!$C$2:$C$501,IF(Dashboard!$C$4="All","*",Dashboard!$C$4),KPI_Data!$D$2:$D$501,IF(Dashboard!$F$4="All","*",Dashboard!$F$4),KPI_Data!$B$2:$B$501,">="&Dashboard!$I$4,KPI_Data!$B$2:$B$501,"<="&Dashboard!$L$4) -> 38479 | E6: =IFERROR(C6/B6,0) -> 2.1515941 | F6: =C6-B6 -> 734266.18
A7: Instagram | B7: =SUMIFS(KPI_Data!$F$2:$F$501,KPI_Data!$C$2:$C$501,A7,KPI_Data!$C$2:$C$501,IF(Dashboard!$C$4="All","*",Dashboard!$C$4),KPI_Data!$D$2:$D$501,IF(Dashboard!$F$4="All","*",Dashboard!$F$4),KPI_Data!$B$2:$B$501,">="&Dashboard!$I$4,KPI_Data!$B$2:$B$501,"<="&Dashboard!$L$4) -> 616798.73 | C7: =SUMIFS(KPI_Data!$J$2:$J$501,KPI_Data!$C$2:$C$501,A7,KPI_Data!$C$2:$C$501,IF(Dashboard!$C$4="All","*",Dashboard!$C$4),KPI_Data!$D$2:$D$501,IF(Dashboard!$F$4="All","*",Dashboard!$F$4),KPI_Data!$B$2:$B$501,">="&Dashboard!$I$4,KPI_Data!$B$2:$B$501,"<="&Dashboard!$L$4) -> 1413738 | D7: =SUMIFS(KPI_Data!$I$2:$I$501,KPI_Data!$C$2:$C$501,A7,KPI_Data!$C$2:$C$501,IF(Dashboard!$C$4="All","*",Dashboard!$C$4),KPI_Data!$D$2:$D$501,IF(Dashboard!$F$4="All","*",Dashboard!$F$4),KPI_Data!$B$2:$B$501,">="&Dashboard!$I$4,KPI_Data!$B$2:$B$501,"<="&Dashboard!$L$4) -> 39603 | E7: =IFERROR(C7/B7,0) -> 2.2920572 | F7: =C7-B7 -> 796939.27
A8: LinkedIn | B8: =SUMIFS(KPI_Data!$F$2:$F$501,KPI_Data!$C$2:$C$501,A8,KPI_Data!$C$2:$C$501,IF(Dashboard!$C$4="All","*",Dashboard!$C$4),KPI_Data!$D$2:$D$501,IF(Dashboard!$F$4="All","*",Dashboard!$F$4),KPI_Data!$B$2:$B$501,">="&Dashboard!$I$4,KPI_Data!$B$2:$B$501,"<="&Dashboard!$L$4) -> 652119.29 | C8: =SUMIFS(KPI_Data!$J$2:$J$501,KPI_Data!$C$2:$C$501,A8,KPI_Data!$C$2:$C$501,IF(Dashboard!$C$4="All","*",Dashboard!$C$4),KPI_Data!$D$2:$D$501,IF(Dashboard!$F$4="All","*",Dashboard!$F$4),KPI_Data!$B$2:$B$501,">="&Dashboard!$I$4,KPI_Data!$B$2:$B$501,"<="&Dashboard!$L$4) -> 1287791.2 | D8: =SUMIFS(KPI_Data!$I$2:$I$501,KPI_Data!$C$2:$C$501,A8,KPI_Data!$C$2:$C$501,IF(Dashboard!$C$4="All","*",Dashboard!$C$4),KPI_Data!$D$2:$D$501,IF(Dashboard!$F$4="All","*",Dashboard!$F$4),KPI_Data!$B$2:$B$501,">="&Dashboard!$I$4,KPI_Data!$B$2:$B$501,"<="&Dashboard!$L$4) -> 36570 | E8: =IFERROR(C8/B8,0) -> 1.9747786 | F8: =C8-B8 -> 635671.93
A9: Twitter | B9: =SUMIFS(KPI_Data!$F$2:$F$501,KPI_Data!$C$2:$C$501,A9,KPI_Data!$C$2:$C$501,IF(Dashboard!$C$4="All","*",Dashboard!$C$4),KPI_Data!$D$2:$D$501,IF(Dashboard!$F$4="All","*",Dashboard!$F$4),KPI_Data!$B$2:$B$501,">="&Dashboard!$I$4,KPI_Data!$B$2:$B$501,"<="&Dashboard!$L$4) -> 653781.56 | C9: =SUMIFS(KPI_Data!$J$2:$J$501,KPI_Data!$C$2:$C$501,A9,KPI_Data!$C$2:$C$501,IF(Dashboard!$C$4="All","*",Dashboard!$C$4),KPI_Data!$D$2:$D$501,IF(Dashboard!$F$4="All","*",Dashboard!$F$4),KPI_Data!$B$2:$B$501,">="&Dashboard!$I$4,KPI_Data!$B$2:$B$501,"<="&Dashboard!$L$4) -> 1193639.2 | D9: =SUMIFS(KPI_Data!$I$2:$I$501,KPI_Data!$C$2:$C$501,A9,KPI_Data!$C$2:$C$501,IF(Dashboard!$C$4="All","*",Dashboard!$C$4),KPI_Data!$D$2:$D$501,IF(Dashboard!$F$4="All","*",Dashboard!$F$4),KPI_Data!$B$2:$B$501,">="&Dashboard!$I$4,KPI_Data!$B$2:$B$501,"<="&Dashboard!$L$4) -> 34412 | E9: =IFERROR(C9/B9,0) -> 1.8257463 | F9: =C9-B9 -> 539857.69
A12: Region-wise Performance
A13: Region | B13: Spend ($) | C13: Revenue ($) | D13: Conversions | E13: ROAS | F13: Profit ($)
A14: East | B14: =SUMIFS(KPI_Data!$F$2:$F$501,KPI_Data!$D$2:$D$501,A14,KPI_Data!$D$2:$D$501,IF(Dashboard!$F$4="All","*",Dashboard!$F$4),KPI_Data!$C$2:$C$501,IF(Dashboard!$C$4="All","*",Dashboard!$C$4),KPI_Data!$B$2:$B$501,">="&Dashboard!$I$4,KPI_Data!$B$2:$B$501,"<="&Dashboard!$L$4) -> 711702.88 | C14: =SUMIFS(KPI_Data!$J$2:$J$501,KPI_Data!$D$2:$D$501,A14,KPI_Data!$D$2:$D$501,IF(Dashboard!$F$4="All","*",Dashboard!$F$4),KPI_Data!$C$2:$C$501,IF(Dashboard!$C$4="All","*",Dashboard!$C$4),KPI_Data!$B$2:$B$501,">="&Dashboard!$I$4,KPI_Data!$B$2:$B$501,"<="&Dashboard!$L$4) -> 1431093.3 | D14: =SUMIFS(KPI_Data!$I$2:$I$501,KPI_Data!$D$2:$D$501,A14,KPI_Data!$D$2:$D$501,IF(Dashboard!$F$4="All","*",Dashboard!$F$4),KPI_Data!$C$2:$C$501,IF(Dashboard!$C$4="All","*",Dashboard!$C$4),KPI_Data!$B$2:$B$501,">="&Dashboard!$I$4,KPI_Data!$B$2:$B$501,"<="&Dashboard!$L$4) -> 41460 | E14: =IFERROR(C14/B14,0) -> 2.0108016 | F14: =C14-B14 -> 719390.43
A15: North | B15: =SUMIFS(KPI_Data!$F$2:$F$501,KPI_Data!$D$2:$D$501,A15,KPI_Data!$D$2:$D$501,IF(Dashboard!$F$4="All","*",Dashboard!$F$4),KPI_Data!$C$2:$C$501,IF(Dashboard!$C$4="All","*",Dashboard!$C$4),KPI_Data!$B$2:$B$501,">="&Dashboard!$I$4,KPI_Data!$B$2:$B$501,"<="&Dashboard!$L$4) -> 838675.44 | C15: =SUMIFS(KPI_Data!$J$2:$J$501,KPI_Data!$D$2:$D$501,A15,KPI_Data!$D$2:$D$501,IF(Dashboard!$F$4="All","*",Dashboard!$F$4),KPI_Data!$C$2:$C$501,IF(Dashboard!$C$4="All","*",Dashboard!$C$4),KPI_Data!$B$2:$B$501,">="&Dashboard!$I$4,KPI_Data!$B$2:$B$501,"<="&Dashboard!$L$4) -> 1706679.9 | D15: =SUMIFS(KPI_Data!$I$2:$I$501,KPI_Data!$D$2:$D$501,A15,KPI_Data!$D$2:$D$501,IF(Dashboard!$F$4="All","*",Dashboard!$F$4),KPI_Data!$C$2:$C$501,IF(Dashboard!$C$4="All","*",Dashboard!$C$4),KPI_Data!$B$2:$B$501,">="&Dashboard!$I$4,KPI_Data!$B$2:$B$501,"<="&Dashboard!$L$4) -> 46771 | E15: =IFERROR(C15/B15,0) -> 2.0349706 | F15: =C15-B15 -> 868004.42
A16: South | B16: =SUMIFS(KPI_Data!$F$2:$F$501,KPI_Data!$D$2:$D$501,A16,KPI_Data!$D$2:$D$501,IF(Dashboard!$F$4="All","*",Dashboard!$F$4),KPI_Data!$C$2:$C$501,IF(Dashboard!$C$4="All","*",Dashboard!$C$4),KPI_Data!$B$2:$B$501,">="&Dashboard!$I$4,KPI_Data!$B$2:$B$501,"<="&Dashboard!$L$4) -> 771410.08 | C16: =SUMIFS(KPI_Data!$J$2:$J$501,KPI_Data!$D$2:$D$501,A16,KPI_Data!$D$2:$D$501,IF(Dashboard!$F$4="All","*",Dashboard!$F$4),KPI_Data!$C$2:$C$501,IF(Dashboard!$C$4="All","*",Dashboard!$C$4),KPI_Data!$B$2:$B$501,">="&Dashboard!$I$4,KPI_Data!$B$2:$B$501,"<="&Dashboard!$L$4) -> 1662610.7 | D16: =SUMIFS(KPI_Data!$I$2:$I$501,KPI_Data!$D$2:$D$501,A16,KPI_Data!$D$2:$D$501,IF(Dashboard!$F$4="All","*",Dashboard!$F$4),KPI_Data!$C$2:$C$501,IF(Dashboard!$C$4="All","*",Dashboard!$C$4),KPI_Data!$B$2:$B$501,">="&Dashboard!$I$4,KPI_Data!$B$2:$B$501,"<="&Dashboard!$L$4) -> 47588 | E16: =IFERROR(C16/B16,0) -> 2.1552878 | F16: =C16-B16 -> 891200.64
A17: West | B17: =SUMIFS(KPI_Data!$F$2:$F$501,KPI_Data!$D$2:$D$501,A17,KPI_Data!$D$2:$D$501,IF(Dashboard!$F$4="All","*",Dashboard!$F$4),KPI_Data!$C$2:$C$501,IF(Dashboard!$C$4="All","*",Dashboard!$C$4),KPI_Data!$B$2:$B$501,">="&Dashboard!$I$4,KPI_Data!$B$2:$B$501,"<="&Dashboard!$L$4) -> 810719.79 | C17: =SUMIFS(KPI_Data!$J$2:$J$501,KPI_Data!$D$2:$D$501,A17,KPI_Data!$D$2:$D$501,IF(Dashboard!$F$4="All","*",Dashboard!$F$4),KPI_Data!$C$2:$C$501,IF(Dashboard!$C$4="All","*",Dashboard!$C$4),KPI_Data!$B$2:$B$501,">="&Dashboard!$I$4,KPI_Data!$B$2:$B$501,"<="&Dashboard!$L$4) -> 1752564.2 | D17: =SUMIFS(KPI_Data!$I$2:$I$501,KPI_Data!$D$2:$D$501,A17,KPI_Data!$D$2:$D$501,IF(Dashboard!$F$4="All","*",Dashboard!$F$4),KPI_Data!$C$2:$C$501,IF(Dashboard!$C$4="All","*",Dashboard!$C$4),KPI_Data!$B$2:$B$501,">="&Dashboard!$I$4,KPI_Data!$B$2:$B$501,"<="&Dashboard!$L$4) -> 48707 | E17: =IFERROR(C17/B17,0) -> 2.1617385 | F17: =C17-B17 -> 941844.4
A20: Monthly Trend
A21: Year-Month | B21: Spend ($) | C21: Revenue ($) | D21: Conversions
A22: 2024-12 | B22: =SUMIFS(KPI_Data!$F$2:$F$501,KPI_Data!$Q$2:$Q$501,A22,KPI_Data!$C$2:$C$501,IF(Dashboard!$C$4="All","*",Dashboard!$C$4),KPI_Data!$D$2:$D$501,IF(Dashboard!$F$4="All","*",Dashboard!$F$4)) -> 387223.67 | C22: =SUMIFS(KPI_Data!$J$2:$J$501,KPI_Data!$Q$2:$Q$501,A22,KPI_Data!$C$2:$C$501,IF(Dashboard!$C$4="All","*",Dashboard!$C$4),KPI_Data!$D$2:$D$501,IF(Dashboard!$F$4="All","*",Dashboard!$F$4)) -> 669060.35 | D22: =SUMIFS(KPI_Data!$I$2:$I$501,KPI_Data!$Q$2:$Q$501,A22,KPI_Data!$C$2:$C$501,IF(Dashboard!$C$4="All","*",Dashboard!$C$4),KPI_Data!$D$2:$D$501,IF(Dashboard!$F$4="All","*",Dashboard!$F$4)) -> 18177
A23: 2025-01 | B23: =SUMIFS(KPI_Data!$F$2:$F$501,KPI_Data!$Q$2:$Q$501,A23,KPI_Data!$C$2:$C$501,IF(Dashboard!$C$4="All","*",Dashboard!$C$4),KPI_Data!$D$2:$D$501,IF(Dashboard!$F$4="All","*",Dashboard!$F$4)) -> 451320.34 | C23: =SUMIFS(KPI_Data!$J$2:$J$501,KPI_Data!$Q$2:$Q$501,A23,KPI_Data!$C$2:$C$501,IF(Dashboard!$C$4="All","*",Dashboard!$C$4),KPI_Data!$D$2:$D$501,IF(Dashboard!$F$4="All","*",Dashboard!$F$4)) -> 1049410.8 | D23: =SUMIFS(KPI_Data!$I$2:$I$501,KPI_Data!$Q$2:$Q$501,A23,KPI_Data!$C$2:$C$501,IF(Dashboard!$C$4="All","*",Dashboard!$C$4),KPI_Data!$D$2:$D$501,IF(Dashboard!$F$4="All","*",Dashboard!$F$4)) -> 28935
A24: 2025-02 | B24: =SUMIFS(KPI_Data!$F$2:$F$501,KPI_Data!$Q$2:$Q$501,A24,KPI_Data!$C$2:$C$501,IF(Dashboard!$C$4="All","*",Dashboard!$C$4),KPI_Data!$D$2:$D$501,IF(Dashboard!$F$4="All","*",Dashboard!$F$4)) -> 519247.21 | C24: =SUMIFS(KPI_Data!$J$2:$J$501,KPI_Data!$Q$2:$Q$501,A24,KPI_Data!$C$2:$C$501,IF(Dashboard!$C$4="All","*",Dashboard!$C$4),KPI_Data!$D$2:$D$501,IF(Dashboard!$F$4="All","*",Dashboard!$F$4)) -> 1178268.8 | D24: =SUMIFS(KPI_Data!$I$2:$I$501,KPI_Data!$Q$2:$Q$501,A24,KPI_Data!$C$2:$C$501,IF(Dashboard!$C$4="All","*",Dashboard!$C$4),KPI_Data!$D$2:$D$501,IF(Dashboard!$F$4="All","*",Dashboard!$F$4)) -> 32571
A25: 2025-03 | B25: =SUMIFS(KPI_Data!$F$2:$F$501,KPI_Data!$Q$2:$Q$501,A25,KPI_Data!$C$2:$C$501,IF(Dashboard!$C$4="All","*",Dashboard!$C$4),KPI_Data!$D$2:$D$501,IF(Dashboard!$F$4="All","*",Dashboard!$F$4)) -> 437450.39 | C25: =SUMIFS(KPI_Data!$J$2:$J$501,KPI_Data!$Q$2:$Q$501,A25,KPI_Data!$C$2:$C$501,IF(Dashboard!$C$4="All","*",Dashboard!$C$4),KPI_Data!$D$2:$D$501,IF(Dashboard!$F$4="All","*",Dashboard!$F$4)) -> 941547.01 | D25: =SUMIFS(KPI_Data!$I$2:$I$501,KPI_Data!$Q$2:$Q$501,A25,KPI_Data!$C$2:$C$501,IF(Dashboard!$C$4="All","*",Dashboard!$C$4),KPI_Data!$D$2:$D$501,IF(Dashboard!$F$4="All","*",Dashboard!$F$4)) -> 26943
A26: 2025-04 | B26: =SUMIFS(KPI_Data!$F$2:$F$501,KPI_Data!$Q$2:$Q$501,A26,KPI_Data!$C$2:$C$501,IF(Dashboard!$C$4="All","*",Dashboard!$C$4),KPI_Data!$D$2:$D$501,IF(Dashboard!$F$4="All","*",Dashboard!$F$4)) -> 649014.28 | C26: =SUMIFS(KPI_Data!$J$2:$J$501,KPI_Data!$Q$2:$Q$501,A26,KPI_Data!$C$2:$C$501,IF(Dashboard!$C$4="All","*",Dashboard!$C$4),KPI_Data!$D$2:$D$501,IF(Dashboard!$F$4="All","*",Dashboard!$F$4)) -> 1226839 | D26: =SUMIFS(KPI_Data!$I$2:$I$501,KPI_Data!$Q$2:$Q$501,A26,KPI_Data!$C$2:$C$501,IF(Dashboard!$C$4="All","*",Dashboard!$C$4),KPI_Data!$D$2:$D$501,IF(Dashboard!$F$4="All","*",Dashboard!$F$4)) -> 36584
A27: 2025-05 | B27: =SUMIFS(KPI_Data!$F$2:$F$501,KPI_Data!$Q$2:$Q$501,A27,KPI_Data!$C$2:$C$501,IF(Dashboard!$C$4="All","*",Dashboard!$C$4),KPI_Data!$D$2:$D$501,IF(Dashboard!$F$4="All","*",Dashboard!$F$4)) -> 558132.99 | C27: =SUMIFS(KPI_Data!$J$2:$J$501,KPI_Data!$Q$2:$Q$501,A27,KPI_Data!$C$2:$C$501,IF(Dashboard!$C$4="All","*",Dashboard!$C$4),KPI_Data!$D$2:$D$501,IF(Dashboard!$F$4="All","*",Dashboard!$F$4)) -> 1149303.8 | D27: =SUMIFS(KPI_Data!$I$2:$I$501,KPI_Data!$Q$2:$Q$501,A27,KPI_Data!$C$2:$C$501,IF(Dashboard!$C$4="All","*",Dashboard!$C$4),KPI_Data!$D$2:$D$501,IF(Dashboard!$F$4="All","*",Dashboard!$F$4)) -> 32256
A28: 2025-06 | B28: =SUMIFS(KPI_Data!$F$2:$F$501,KPI_Data!$Q$2:$Q$501,A28,KPI_Data!$C$2:$C$501,IF(Dashboard!$C$4="All","*",Dashboard!$C$4),KPI_Data!$D$2:$D$501,IF(Dashboard!$F$4="All","*",Dashboard!$F$4)) -> 130119.31 | C28: =SUMIFS(KPI_Data!$J$2:$J$501,KPI_Data!$Q$2:$Q$501,A28,KPI_Data!$C$2:$C$501,IF(Dashboard!$C$4="All","*",Dashboard!$C$4),KPI_Data!$D$2:$D$501,IF(Dashboard!$F$4="All","*",Dashboard!$F$4)) -> 338518.38 | D28: =SUMIFS(KPI_Data!$I$2:$I$501,KPI_Data!$Q$2:$Q$501,A28,KPI_Data!$C$2:$C$501,IF(Dashboard!$C$4="All","*",Dashboard!$C$4),KPI_Data!$D$2:$D$501,IF(Dashboard!$F$4="All","*",Dashboard!$F$4)) -> 9060
A31: Overall Funnel
A32: Stage | B32: Count
A33: Impressions | B33: =SUMIFS(KPI_Data!$G$2:$G$501,KPI_Data!$C$2:$C$501,IF(Dashboard!$C$4="All","*",Dashboard!$C$4),KPI_Data!$D$2:$D$501,IF(Dashboard!$F$4="All","*",Dashboard!$F$4),KPI_Data!$B$2:$B$501,">="&Dashboard!$I$4,KPI_Data!$B$2:$B$501,"<="&Dashboard!$L$4) -> 62386067
A34: Clicks | B34: =SUMIFS(KPI_Data!$H$2:$H$501,KPI_Data!$C$2:$C$501,IF(Dashboard!$C$4="All","*",Dashboard!$C$4),KPI_Data!$D$2:$D$501,IF(Dashboard!$F$4="All","*",Dashboard!$F$4),KPI_Data!$B$2:$B$501,">="&Dashboard!$I$4,KPI_Data!$B$2:$B$501,"<="&Dashboard!$L$4) -> 1814121
A35: Conversions | B35: =SUMIFS(KPI_Data!$I$2:$I$501,KPI_Data!$C$2:$C$501,IF(Dashboard!$C$4="All","*",Dashboard!$C$4),KPI_Data!$D$2:$D$501,IF(Dashboard!$F$4="All","*",Dashboard!$F$4),KPI_Data!$B$2:$B$501,">="&Dashboard!$I$4,KPI_Data!$B$2:$B$501,"<="&Dashboard!$L$4) -> 184526
A38: Budget Allocation by Channel
A39: Channel | B39: Budget ($)
A40: Facebook | B40: =SUMIFS(KPI_Data!$E$2:$E$501,KPI_Data!$C$2:$C$501,A40,KPI_Data!$C$2:$C$501,IF(Dashboard!$C$4="All","*",Dashboard!$C$4),KPI_Data!$D$2:$D$501,IF(Dashboard!$F$4="All","*",Dashboard!$F$4),KPI_Data!$B$2:$B$501,">="&Dashboard!$I$4,KPI_Data!$B$2:$B$501,"<="&Dashboard!$L$4) -> 609756.67
A41: Google Ads | B41: =SUMIFS(KPI_Data!$E$2:$E$501,KPI_Data!$C$2:$C$501,A41,KPI_Data!$C$2:$C$501,IF(Dashboard!$C$4="All","*",Dashboard!$C$4),KPI_Data!$D$2:$D$501,IF(Dashboard!$F$4="All","*",Dashboard!$F$4),KPI_Data!$B$2:$B$501,">="&Dashboard!$I$4,KPI_Data!$B$2:$B$501,"<="&Dashboard!$L$4) -> 658766.93
A42: Instagram | B42: =SUMIFS(KPI_Data!$E$2:$E$501,KPI_Data!$C$2:$C$501,A42,KPI_Data!$C$2:$C$501,IF(Dashboard!$C$4="All","*",Dashboard!$C$4),KPI_Data!$D$2:$D$501,IF(Dashboard!$F$4="All","*",Dashboard!$F$4),KPI_Data!$B$2:$B$501,">="&Dashboard!$I$4,KPI_Data!$B$2:$B$501,"<="&Dashboard!$L$4) -> 655972.1
A43: LinkedIn | B43: =SUMIFS(KPI_Data!$E$2:$E$501,KPI_Data!$C$2:$C$501,A43,KPI_Data!$C$2:$C$501,IF(Dashboard!$C$4="All","*",Dashboard!$C$4),KPI_Data!$D$2:$D$501,IF(Dashboard!$F$4="All","*",Dashboard!$F$4),KPI_Data!$B$2:$B$501,">="&Dashboard!$I$4,KPI_Data!$B$2:$B$501,"<="&Dashboard!$L$4) -> 689111.07
A44: Twitter | B44: =SUMIFS(KPI_Data!$E$2:$E$501,KPI_Data!$C$2:$C$501,A44,KPI_Data!$C$2:$C$501,IF(Dashboard!$C$4="All","*",Dashboard!$C$4),KPI_Data!$D$2:$D$501,IF(Dashboard!$F$4="All","*",Dashboard!$F$4),KPI_Data!$B$2:$B$501,">="&Dashboard!$I$4,KPI_Data!$B$2:$B$501,"<="&Dashboard!$L$4) -> 698066.24

Sheet KPI_Data
A1: Campaign_ID | B1: Date | C1: Channel | D1: Region | E1: Budget ($) | F1: Spend ($) | G1: Impressions | H1: Clicks | I1: Conversions | J1: Revenue ($) | K1: CTR | L1: CPC | M1: CPA | N1: ROAS | O1: Profit ($) | P1: Profit Margin % | Q1: Year-Month
A2: =Raw_Data!A2 -> C0498 | B2: =Raw_Data!B2 -> 45636 | C2: =Raw_Data!C2 -> Facebook | D2: =Raw_Data!D2 -> East | E2: =Raw_Data!E2 -> 5612.76 | F2: =Raw_Data!F2 -> 4872.89 | G2: =Raw_Data!G2 -> 107940 | H2: =Raw_Data!H2 -> 2915 | ... J2: =Raw_Data!J2 -> 3329.38 | K2: =IFERROR(H2/G2,0) -> 0.027005744 | L2: =IFERROR(F2/H2,0) -> 1.6716604 | M2: =IFERROR(F2/I2,0) -> 32.485933 | N2: =IFERROR(J2/F2,0) -> 0.68324547 | O2: =J2-F2 -> -1543.51 | P2: =IFERROR(O2/J2*100,0) -> -46.360283 | Q2: =TEXT(B2,"YYYY-MM") -> 2024-12
A3: =Raw_Data!A3 -> C0170 | B3: =Raw_Data!B3 -> 45636 | C3: =Raw_Data!C3 -> Twitter | D3: =Raw_Data!D3 -> North | E3: =Raw_Data!E3 -> 8757.76 | F3: =Raw_Data!F3 -> 9501.64 | G3: =Raw_Data!G3 -> 75315 | H3: =Raw_Data!H3 -> 1121 | ... J3: =Raw_Data!J3 -> 3550.58 | K3: =IFERROR(H3/G3,0) -> 0.014884153 | L3: =IFERROR(F3/H3,0) -> 8.4760393 | M3: =IFERROR(F3/I3,0) -> 111.784 | N3: =IFERROR(J3/F3,0) -> 0.37368075 | O3: =J3-F3 -> -5951.06 | P3: =IFERROR(O3/J3*100,0) -> -167.60811 | Q3: =TEXT(B3,"YYYY-MM") -> 2024-12
A4: =Raw_Data!A4 -> C0215 | B4: =Raw_Data!B4 -> 45636 | C4: =Raw_Data!C4 -> Google Ads | D4: =Raw_Data!D4 -> East | E4: =Raw_Data!E4 -> 4480.14 | F4: =Raw_Data!F4 -> 4024.28 | G4: =Raw_Data!G4 -> 177951 | H4: =Raw_Data!H4 -> 3898 | ... J4: =Raw_Data!J4 -> 6676.78 | K4: =IFERROR(H4/G4,0) -> 0.021904906 | L4: =IFERROR(F4/H4,0) -> 1.0323961 | M4: =IFERROR(F4/I4,0) -> 14.220071 | N4: =IFERROR(J4/F4,0) -> 1.6591241 | O4: =J4-F4 -> 2652.5 | P4: =IFERROR(O4/J4*100,0) -> 39.727234 | Q4: =TEXT(B4,"YYYY-MM") -> 2024-12
A5: =Raw_Data!A5 -> C0077 | B5: =Raw_Data!B5 -> 45636 | C5: =Raw_Data!C5 -> Twitter | D5: =Raw_Data!D5 -> East | E5: =Raw_Data!E5 -> 9244.33 | F5: =Raw_Data!F5 -> 9145.8 | G5: =Raw_Data!G5 -> 55244 | H5: =Raw_Data!H5 -> 2028 | ... J5: =Raw_Data!J5 -> 14030.19 | K5: =IFERROR(H5/G5,0) -> 0.036709869 | L5: =IFERROR(F5/H5,0) -> 4.5097633 | M5: =IFERROR(F5/I5,0) -> 28.580625 | N5: =IFERROR(J5/F5,0) -> 1.5340583 | O5: =J5-F5 -> 4884.39 | P5: =IFERROR(O5/J5*100,0) -> 34.813427 | Q5: =TEXT(B5,"YYYY-MM") -> 2024-12
A6: =Raw_Data!A6 -> C0175 | B6: =Raw_Data!B6 -> 45637 | C6: =Raw_Data!C6 -> Instagram | D6: =Raw_Data!D6 -> West | E6: =Raw_Data!E6 -> 9789.4 | F6: =Raw_Data!F6 -> 10304.67 | G6: =Raw_Data!G6 -> 143568 | H6: =Raw_Data!H6 -> 6593 | ... J6: =Raw_Data!J6 -> 39235.23 | K6: =IFERROR(H6/G6,0) -> 0.04592249 | L6: =IFERROR(F6/H6,0) -> 1.5629713 | M6: =IFERROR(F6/I6,0) -> 11.858078 | N6: =IFERROR(J6/F6,0) -> 3.8075193 | O6: =J6-F6 -> 28930.56 | P6: =IFERROR(O6/J6*100,0) -> 73.73618 | Q6: =TEXT(B6,"YYYY-MM") -> 2024-12
A7: =Raw_Data!A7 -> C0210 | B7: =Raw_Data!B7 -> 45637 | C7: =Raw_Data!C7 -> LinkedIn | D7: =Raw_Data!D7 -> West | E7: =Raw_Data!E7 -> 8232.3 | F7: =Raw_Data!F7 -> 6676.44 | G7: =Raw_Data!G7 -> 195298 | H7: =Raw_Data!H7 -> 3830 | ... J7: =Raw_Data!J7 -> 9374.86 | K7: =IFERROR(H7/G7,0) -> 0.019611056 | L7: =IFERROR(F7/H7,0) -> 1.7431958 | M7: =IFERROR(F7/I7,0) -> 19.636588 | N7: =IFERROR(J7/F7,0) -> 1.4041705 | O7: =J7-F7 -> 2698.42 | P7: =IFERROR(O7/J7*100,0) -> 28.783577 | Q7: =TEXT(B7,"YYYY-MM") -> 2024-12
A8: =Raw_Data!A8 -> C0256 | B8: =Raw_Data!B8 -> 45637 | C8: =Raw_Data!C8 -> Instagram | D8: =Raw_Data!D8 -> South | E8: =Raw_Data!E8 -> 6989.23 | F8: =Raw_Data!F8 -> 7190.08 | G8: =Raw_Data!G8 -> 119284 | H8: =Raw_Data!H8 -> 1389 | ... J8: =Raw_Data!J8 -> 9769.93 | K8: =IFERROR(H8/G8,0) -> 0.011644479 | L8: =IFERROR(F8/H8,0) -> 5.1764435 | M8: =IFERROR(F8/I8,0) -> 34.076209 | N8: =IFERROR(J8/F8,0) -> 1.3588069 | O8: =J8-F8 -> 2579.85 | P8: =IFERROR(O8/J8*100,0) -> 26.406023 | Q8: =TEXT(B8,"YYYY-MM") -> 2024-12
A9: =Raw_Data!A9 -> C0338 | B9: =Raw_Data!B9 -> 45637 | C9: =Raw_Data!C9 -> Twitter | D9: =Raw_Data!D9 -> East | E9: =Raw_Data!E9 -> 9913.68 | F9: =Raw_Data!F9 -> 10738.67 | G9: =Raw_Data!G9 -> 123947 | H9: =Raw_Data!H9 -> 4068 | ... J9: =Raw_Data!J9 -> 8473.12 | K9: =IFERROR(H9/G9,0) -> 0.03282048 | L9: =IFERROR(F9/H9,0) -> 2.6397911 | M9: =IFERROR(F9/I9,0) -> 26.846675 | N9: =IFERROR(J9/F9,0) -> 0.78902881 | O9: =J9-F9 -> -2265.55 | P9: =IFERROR(O9/J9*100,0) -> -26.738085 | Q9: =TEXT(B9,"YYYY-MM") -> 2024-12
A10: =Raw_Data!A10 -> C0198 | B10: =Raw_Data!B10 -> 45638 | C10: =Raw_Data!C10 -> LinkedIn | D10: =Raw_Data!D10 -> West | E10: =Raw_Data!E10 -> 7486.12 | F10: =Raw_Data!F10 -> 6397.37 | G10: =Raw_Data!G10 -> 150378 | H10: =Raw_Data!H10 -> 1516 | ... J10: =Raw_Data!J10 -> 8169.53 | K10: =IFERROR(H10/G10,0) -> 0.010081262 | L10: =IFERROR(F10/H10,0) -> 4.2199011 | M10: =IFERROR(F10/I10,0) -> 23.782045 | N10: =IFERROR(J10/F10,0) -> 1.2770138 | O10: =J10-F10 -> 1772.16 | P10: =IFERROR(O10/J10*100,0) -> 21.692313 | Q10: =TEXT(B10,"YYYY-MM") -> 2024-12
A11: =Raw_Data!A11 -> C0087 | B11: =Raw_Data!B11 -> 45639 | C11: =Raw_Data!C11 -> Twitter | D11: =Raw_Data!D11 -> North | E11: =Raw_Data!E11 -> 6990.43 | F11: =Raw_Data!F11 -> 5796.14 | G11: =Raw_Data!G11 -> 97675 | H11: =Raw_Data!H11 -> 4253 | ... J11: =Raw_Data!J11 -> 16149.09 | K11: =IFERROR(H11/G11,0) -> 0.04354236 | L11: =IFERROR(F11/H11,0) -> 1.3628356 | M11: =IFERROR(F11/I11,0) -> 13.800333 | N11: =IFERROR(J11/F11,0) -> 2.7861801 | O11: =J11-F11 -> 10352.95 | P11: =IFERROR(O11/J11*100,0) -> 64.108566 | Q11: =TEXT(B11,"YYYY-MM") -> 2024-12
A12: =Raw_Data!A12 -> C0460 | B12: =Raw_Data!B12 -> 45639 | C12: =Raw_Data!C12 -> Instagram | D12: =Raw_Data!D12 -> South | E12: =Raw_Data!E12 -> 6603.72 | F12: =Raw_Data!F12 -> 5994.66 | G12: =Raw_Data!G12 -> 55887 | H12: =Raw_Data!H12 -> 1060 | ... J12: =Raw_Data!J12 -> 7633.28 | K12: =IFERROR(H12/G12,0) -> 0.018966844 | L12: =IFERROR(F12/H12,0) -> 5.6553396 | M12: =IFERROR(F12/I12,0) -> 29.676535 | N12: =IFERROR(J12/F12,0) -> 1.2733466 | O12: =J12-F12 -> 1638.62 | P12: =IFERROR(O12/J12*100,0) -> 21.466788 | Q12: =TEXT(B12,"YYYY-MM") -> 2024-12
A13: =Raw_Data!A13 -> C0114 | B13: =Raw_Data!B13 -> 45639 | C13: =Raw_Data!C13 -> LinkedIn | D13: =Raw_Data!D13 -> West | E13: =Raw_Data!E13 -> 3684.84 | F13: =Raw_Data!F13 -> 3491.33 | G13: =Raw_Data!G13 -> 99153 | H13: =Raw_Data!H13 -> 2036 | ... J13: =Raw_Data!J13 -> 13065.99 | K13: =IFERROR(H13/G13,0) -> 0.020533922 | L13: =IFERROR(F13/H13,0) -> 1.7147986 | M13: =IFERROR(F13/I13,0) -> 9.1396073 | N13: =IFERROR(J13/F13,0) -> 3.7424105 | O13: =J13-F13 -> 9574.66 | P13: =IFERROR(O13/J13*100,0) -> 73.279254 | Q13: =TEXT(B13,"YYYY-MM") -> 2024-12
... A501: =Raw_Data!A501 -> C0357 | B501: =Raw_Data!B501 -> 45818 | C501: =Raw_Data!C501 -> Google Ads | D501: =Raw_Data!D501 -> East | E501: =Raw_Data!E501 -> 5482.36 | F501: =Raw_Data!F501 -> 4858.31 | G501: =Raw_Data!G501 -> 99224 | H501: =Raw_Data!H501 -> 3662 | ... J501: =Raw_Data!J501 -> 6731.19 | K501: =IFERROR(H501/G501,0) -> 0.036906394 | L501: =IFERROR(F501/H501,0) -> 1.3266821 | M501: =IFERROR(F501/I501,0) -> 20.851116 | N501: =IFERROR(J501/F501,0) -> 1.3855003 | O501: =J501-F501 -> 1872.88 | P501: =IFERROR(O501/J501*100,0) -> 27.823906 | Q501: =TEXT(B501,"YYYY-MM") -> 2025-06

Sheet Raw_Data
A1: Campaign_ID | B1: Date | C1: Channel | D1: Region | E1: Budget ($) | F1: Spend ($) | G1: Impressions | H1: Clicks | I1: Conversions | J1: Revenue ($)
A2: C0498 | B2: 45636 | C2: Facebook | D2: East | E2: 5612.76 | F2: 4872.89 | G2: 107940 | H2: 2915 | I2: 150 | J2: 3329.38
A3: C0170 | B3: 45636 | C3: Twitter | D3: North | E3: 8757.76 | F3: 9501.64 | G3: 75315 | H3: 1121 | I3: 85 | J3: 3550.58
A4: C0215 | B4: 45636 | C4: Google Ads | D4: East | E4: 4480.14 | F4: 4024.28 | G4: 177951 | H4: 3898 | I4: 283 | J4: 6676.78
A5: C0077 | B5: 45636 | C5: Twitter | D5: East | E5: 9244.33 | F5: 9145.8 | G5: 55244 | H5: 2028 | I5: 320 | J5: 14030.19
A6: C0175 | B6: 45637 | C6: Instagram | D6: West | E6: 9789.4 | F6: 10304.67 | G6: 143568 | H6: 6593 | I6: 869 | J6: 39235.23
A7: C0210 | B7: 45637 | C7: LinkedIn | D7: West | E7: 8232.3 | F7: 6676.44 | G7: 195298 | H7: 3830 | I7: 340 | J7: 9374.86
A8: C0256 | B8: 45637 | C8: Instagram | D8: South | E8: 6989.23 | F8: 7190.08 | G8: 119284 | H8: 1389 | I8: 211 | J8: 9769.93
A9: C0338 | B9: 45637 | C9: Twitter | D9: East | E9: 9913.68 | F9: 10738.67 | G9: 123947 | H9: 4068 | I9: 400 | J9: 8473.12
A10: C0198 | B10: 45638 | C10: LinkedIn | D10: West | E10: 7486.12 | F10: 6397.37 | G10: 150378 | H10: 1516 | I10: 269 | J10: 8169.53
A11: C0087 | B11: 45639 | C11: Twitter | D11: North | E11: 6990.43 | F11: 5796.14 | G11: 97675 | H11: 4253 | I11: 420 | J11: 16149.09
A12: C0460 | B12: 45639 | C12: Instagram | D12: South | E12: 6603.72 | F12: 5994.66 | G12: 55887 | H12: 1060 | I12: 202 | J12: 7633.28
A13: C0114 | B13: 45639 | C13: LinkedIn | D13: West | E13: 3684.84 | F13: 3491.33 | G13: 99153 | H13: 2036 | I13: 382 | J13: 13065.99
... A501: C0357 | B501: 45818 | C501: Google Ads | D501: East | E501: 5482.36 | F501: 4858.31 | G501: 99224 | H501: 3662 | I501: 233 | J501: 6731.19
